{
    "status": "ok",
    "totalResults": 34,
    "articles": [
        {
            "source": {
                "id": null,
                "name": "CNEWS.fr"
            },
            "author": "CNEWS",
            "title": "Robert Broussard, Ange Mancini... Pourquoi Emmanuel Macron a-t-il invité à dîner mardi soir des grandes figures de la police ? - CNEWS",
            "description": "Les anciens «grands flics» ont été reçus mardi soir à l’Élysée pour un dîner autour d'Emmanuel Macron. Le chef de l’État a souhaité leur rendre hommage et avoir leur avis sur la profession de policier ainsi que les évolutions apportées au métier durant les de…",
            "url": "https://www.cnews.fr/france/2022-10-04/robert-broussard-ange-mancini-pourquoi-emmanuel-macron-t-il-invite-diner-mardi",
            "urlToImage": "https://static.cnews.fr/sites/default/files/000_32kl9gg-taille1200_633c49640d7bc_0.jpg",
            "publishedAt": "2022-10-04T23:23:52Z",
            "content": "Publié le\r\n04/10/2022 à 23:23 -\r\nMis à jour le\r\n04/10/2022 à 23:27\r\nLes anciens «grands flics» ont été reçus mardi soir à l’Élysée pour un dîner autour d'Emmanuel Macron. Le chef de l’État a souhaité… [+2752 chars]"
        },
        {
            "source": {
                "id": "le-monde",
                "name": "Le Monde"
            },
            "author": "Le Monde avec AFP",
            "title": "Au Brésil, des ralliements de poids pour Lula et Bolsonaro avant le second tour de la présidentielle - Le Monde",
            "description": "Les grandes manœuvres ont commencé au surlendemain du premier tour qui a vu Luiz Inacio Lula da Silva, icône de la gauche, remporter 48,4 % des voix, devant le président sortant, Jair Bolsonaro, dont le score a été meilleur que prévu, avec 43,2 %.",
            "url": "https://www.lemonde.fr/international/article/2022/10/05/bresil-ralliements-de-poids-pour-lula-et-bolsonaro-avant-le-second-tour_6144414_3210.html",
            "urlToImage": "https://img.lemde.fr/2022/10/04/0/102/5932/3955/1440/960/60/0/a27472e_5369514-01-06.jpg",
            "publishedAt": "2022-10-04T22:32:43Z",
            "content": "Le président sortant Jair Bolsonaro, à gauche, et son opposant et concurrent à la présidence, Luiz Inacio Lula da Silva, à droite. EVARISTO SA / AFP\r\nLes deux adversaires de la présidentielle au Brés… [+4994 chars]"
        },
        {
            "source": {
                "id": null,
                "name": "Eurosport.fr"
            },
            "author": "Guillaume Maillard-Pacini",
            "title": "Ligue des champions - Après Inter - Barça (1-0) : Xavi se dit \"indigné\" et \"énervé\" par l'arbitrage - Eurosport FR",
            "description": "LIGUE DES CHAMPIONS - Le Barça ne digère pas le penalty non accordé.",
            "url": "https://www.eurosport.fr/football/ligue-des-champions/2022-2023/ligue-des-champions-apres-inter-barca-1-0-xavi-se-dit-indigne-et-enerve-par-le-penalty-non-accorde_sto9172582/story.shtml",
            "urlToImage": "https://i.eurosport.com/2022/10/04/3465136-70687888-2560-1440.jpg",
            "publishedAt": "2022-10-04T22:08:00Z",
            "content": "La main de Dumfries lors de Inter-Barça, Movistar\r\nCrédit: Twitter"
        },
        {
            "source": {
                "id": null,
                "name": "BFMTV"
            },
            "author": null,
            "title": "Poursuivi en justice par les actionnaires, Elon Musk accepte finalement de racheter Twitter - Tech & Co",
            "description": "L'homme d'affaires devait faire face à l'entreprise en justice à partir du 17 octobre, pour avoir annulé une première offre proposée au printemps 2022.",
            "url": "https://www.bfmtv.com/tech/twitter/elon-musk-souhaite-a-nouveau-racheter-twitter_AN-202210040611.html",
            "urlToImage": "https://images.bfmtv.com/Nq4epuUjbvN51BA58VGwncEGpjE=/0x39:768x471/768x0/images/Le-milliardaire-Elon-Musk-presente-la-mega-fusee-de-SpaceX-Starship-le-10-fevrier-2022-pres-de-Boca-Chica-dans-le-sud-du-Texas-1233874.jpg",
            "publishedAt": "2022-10-04T21:51:10Z",
            "content": "L'homme d'affaires devait faire face à l'entreprise en justice à partir du 17 octobre, pour avoir annulé une première offre proposée au printemps 2022.\r\nC'est un nouvel épisode pour le moins inattend… [+1992 chars]"
        },
        {
            "source": {
                "id": "lequipe",
                "name": "L'equipe"
            },
            "author": "Rédaction",
            "title": "Igor Tudor (OM) après la victoire contre le Sporting : « Balerdi est un très bon joueur » - L'Équipe",
            "description": "En conférence de presse après la victoire de l'OM face au Sporting Portugal en Ligue des champions (4-1), l'entraîneur marseillais Igor Tudor n'a pas tari d'éloges son défenseur argentin Leonardo Balerdi.",
            "url": "https://www.lequipe.fr/Football/Actualites/Igor-tudor-om-apres-la-victoire-contre-le-sporting-balerdi-est-un-tres-bon-joueur/1357583",
            "urlToImage": "https://medias.lequipe.fr/img-photo-jpg/l-entraineur-de-l-om-igor-tudor-ce-mardi-soir-f-faugere-l-equipe/1500000001695165/0:0,1996:1331-640-427-75/687ff.jpg",
            "publishedAt": "2022-10-04T21:18:23Z",
            "content": "Igor Tudor, l'entraîneur de l'OM, après la victoire face au Sporting Portugal (4-1) : « Après un match comme ça, je ne veux pas parler des individualités. Je pense qu'on a fait un match collectif trè… [+800 chars]"
        },
        {
            "source": {
                "id": null,
                "name": "20 Minutes"
            },
            "author": "Louis Pillot",
            "title": "Russie : Avant une audience en appel pour la basketteuse Brittney Griner, Washington dénonce un « simulacre » - 20 Minutes",
            "description": "L’Américaine a été condamnée à une lourde peine de prison, dans un procès pour détention de cannabis aux dimensions géopolitiques",
            "url": "https://www.20minutes.fr/monde/4003777-20221004-russie-avant-audience-appel-basketteuse-brittney-griner-washington-denonce-simulacre",
            "urlToImage": "https://img.20mn.fr/qMuEHbvLRcat7vGdRa7liik/1200x768_file-wnba-star-and-two-time-olympic-gold-medalist-brittney-griner-is-escorted-from-a-courtroom-after-a-hearing-in-khimki-just-outside-moscow-russia-on-aug-4-2022-the-moscow-region-s-court-on-monday-oct-3-2022-set-a-date-for-american-basketball-star-brittney-griner-s-appeal-against-her-nine-year-prison-sentence-for-drug-possession-scheduling-the-hearing-for-oct-25-ap-photo-alexander-zemlianichenko-file-xaz116-22276612390587-file-photo-2210031910",
            "publishedAt": "2022-10-04T20:13:42Z",
            "content": "« Nous sommes au courant de l’annonce par la Russie d’un autre simulacre de justice qui sera imposé à Brittney Griner », star du basket féminin condamnée à une lourde peine de prison par la justice r… [+1292 chars]"
        },
        {
            "source": {
                "id": null,
                "name": "jeuxvideo.com"
            },
            "author": "JeromeJoffard",
            "title": "Après Cyberpunk 2077 et The Witcher, CD Projekt présente Hadar, une toute nouvelle licence - jeuxvideo.com",
            "description": "Quand CD Projekt prend la parole, il ne fait pas les choses à moitié. Aujourd'hui, c'est pas loin de sept nouveaux projets que dévoile l'éditeur polonais, dont un certain Hadar. Un projet supplémentaire signée CD Projekt C'est par le biais d'un gigantesque th…",
            "url": "https://www.jeuxvideo.com/news/1646905/apres-cyberpunk-2077-et-the-witcher-cd-projekt-presente-hadar-une-toute-nouvelle-licence.htm",
            "urlToImage": "https://image.jeuxvideo.com/medias-md/166491/1664912620-1381-card.png",
            "publishedAt": "2022-10-04T19:54:42Z",
            "content": "Quand CD Projekt prend la parole, il ne fait pas les choses à moitié. Aujourd'hui, c'est pas loin de sept nouveaux projets que dévoile l'éditeur polonais, dont un certain Hadar.Un projet supplémentai… [+1736 chars]"
        },
        {
            "source": {
                "id": null,
                "name": "Francetvinfo.fr"
            },
            "author": null,
            "title": "Jeux asiatiques d'hiver en Arabie saoudite : \"Écrire l'histoire avec le sport, c'est essentiel pour un régime autoritaire\", analyse un spécialiste en géopolitique du sport - franceinfo",
            "description": "L'Arabie saoudite a été désignée pour accueillir les Jeux asiatiques d'hiver dans sept ans. L'événement sportif sera organisé à Neom, une mégapole futuriste en construction dans le nord-ouest du royaume désertique, a annoncé mardi le Conseil olympique d'Asie …",
            "url": "https://www.francetvinfo.fr/monde/environnement/jeux-asiatiques-d-hiver-en-arabie-saoudite-ecrire-l-histoire-avec-le-sport-c-est-essentiel-pour-un-regime-autoritaire-analyse-un-specialiste-en-geopolitique-du-sport_5397604.html",
            "urlToImage": "https://www.francetvinfo.fr/pictures/sPOQEpGNlktM71cK2uCmkpkbe1c/1500x843/2022/10/04/phpciVLRs.jpg",
            "publishedAt": "2022-10-04T19:52:51Z",
            "content": "L'Arabie saoudite a été désignée pour accueillir les Jeux asiatiques d'hiver dans sept ans. L'événement sportif sera organisé à Neom, une mégapole futuriste en construction dans le nord-ouest du roya… [+2796 chars]"
        },
        {
            "source": {
                "id": null,
                "name": "Francetvinfo.fr"
            },
            "author": null,
            "title": "Guerre en Ukraine : ce qu'il faut retenir de la journée du mardi 4 octobre - franceinfo",
            "description": "La percée ukrainienne se poursuit. Une carte montrée mardi par le ministère russe de la Défense fait état d'un recul important des forces russes dans la région de Kherson, dans le sud de l'Ukraine.",
            "url": "https://www.francetvinfo.fr/monde/europe/manifestations-en-ukraine/guerre-en-ukraine-ce-qu-il-faut-retenir-de-la-journee-du-mardi-4-octobre_5397637.html",
            "urlToImage": "https://www.francetvinfo.fr/pictures/2VulsL8JEbe5DE2toXjeRzcSA74/1500x843/2022/10/04/phpYLvedX.jpg",
            "publishedAt": "2022-10-04T19:42:31Z",
            "content": "La percée ukrainienne se poursuit. Une carte montrée mardi par le ministère russe de la Défense fait état d'un recul important des forces russes dans la région de Kherson, dans le sud de l'Ukraine.Un… [+4344 chars]"
        },
        {
            "source": {
                "id": null,
                "name": "Pure People"
            },
            "author": "Bertrand Bielle",
            "title": "Mask Singer - La Tigresse démasquée : Vitaa a de suite reconnu la star sous ce costume - Pure People",
            "description": "Ce mardi 4 octobre, TF1 a diffusé la demi-finale de \"Mask Singer 2022\". Et en cours d'émission, un nouveau guest a fait son apparition sous le costume d'une Tigresse. De qui s'agissait-il ? Réponse tout de suite puique ce nouveau personnage vient d'être démas…",
            "url": "https://www.purepeople.com/article/mask-singer-la-tigresse-demasquee-vitaa-a-de-suite-reconnu-la-star-sous-ce-costume_a498251/1",
            "urlToImage": "https://static1.purepeople.com/articles/1/49/82/51/@/7245915-la-tigresse-dans-mask-singer-opengraph_1200-3.png",
            "publishedAt": "2022-10-04T19:31:00Z",
            "content": "La saison 4 de Mask Singer prendra prochainement fin. Ce mardi 4 octobre 2022, TF1 a diffusé la demi-finale de l'émission présentée par Camille Combal. Et les enquêteurs Kev Adams, Chantal Ladesou, V… [+1374 chars]"
        },
        {
            "source": {
                "id": "google-news",
                "name": "Google News"
            },
            "author": null,
            "title": "La Russie multiplie les manœuvres militaires de dissuasion nucléaire - Le Figaro",
            "description": null,
            "url": "https://news.google.com/__i/rss/rd/articles/CBMidGh0dHBzOi8vd3d3LmxlZmlnYXJvLmZyL2ludGVybmF0aW9uYWwvbGEtcnVzc2llLW11bHRpcGxpZS1sZXMtbWFub2V1dnJlcy1taWxpdGFpcmVzLWRlLWRpc3N1YXNpb24tbnVjbGVhaXJlLTIwMjIxMDA00gF0aHR0cHM6Ly9hbXAubGVmaWdhcm8uZnIvaW50ZXJuYXRpb25hbC9sYS1ydXNzaWUtbXVsdGlwbGllLWxlcy1tYW5vZXV2cmVzLW1pbGl0YWlyZXMtZGUtZGlzc3Vhc2lvbi1udWNsZWFpcmUtMjAyMjEwMDQ?oc=5",
            "urlToImage": null,
            "publishedAt": "2022-10-04T19:29:42Z",
            "content": null
        },
        {
            "source": {
                "id": null,
                "name": "20 Minutes"
            },
            "author": "Pigiste Chaud",
            "title": "L’Etat a lancé le processus de renationalisation complète d’EDF - 20 Minutes",
            "description": "L’État a déposé son projet d’offre publique d’achat auprès de l’Autorité des marchés financiers",
            "url": "https://www.20minutes.fr/economie/4003768-20221004-etat-lance-processus-renationalisation-complete-edf",
            "urlToImage": "https://img.20mn.fr/cKZuS1zuRNOt8YeeRk9QHyk/1200x768_files-this-file-photograph-taken-on-june-8-2022-shows-the-logo-of-french-electricity-giant-edf-at-the-international-cybersecurity-forum-fic-in-lille-northern-france-french-state-energy-firm-edf-said-september-15-2022-that-lower-electricity-production-due-to-stoppages-of-nuclear-reactors-would-sap-its-operating-profit-by-29-billion-euros-29-billion-in-2022-worse-than-previously-forecast-photo-by-denis-charlet-afp",
            "publishedAt": "2022-10-04T18:25:29Z",
            "content": "Cette fois, on y est. L’État français a officiellement lancé mardi le processus de renationalisation de l’entreprise EDF. Une opération voulue par le gouvernement pour relancer le nucléaire après une… [+1167 chars]"
        },
        {
            "source": {
                "id": null,
                "name": "YouTube"
            },
            "author": null,
            "title": "Coup de pompe chez Total : à la recherche du précieux carburant - Le Parisien",
            "description": "Dans de nombreuses stations essence Total-Energies, il est difficile de trouver du carburant depuis plusieurs semaines. En cause, la réduction à la pompe de ...",
            "url": "https://www.youtube.com/watch?v=31fD8rTGVjM",
            "urlToImage": "https://i.ytimg.com/vi/31fD8rTGVjM/maxresdefault.jpg",
            "publishedAt": "2022-10-04T18:23:19Z",
            "content": null
        },
        {
            "source": {
                "id": "google-news",
                "name": "Google News"
            },
            "author": null,
            "title": "Julien Bayou et Sandrine Rousseau, les dessous d'une guerre totale - Le Figaro",
            "description": null,
            "url": "https://news.google.com/__i/rss/rd/articles/CBMibGh0dHBzOi8vd3d3LmxlZmlnYXJvLmZyL3BvbGl0aXF1ZS9qdWxpZW4tYmF5b3UtZXQtc2FuZHJpbmUtcm91c3NlYXUtbGVzLWRlc3NvdXMtZC11bmUtZ3VlcnJlLXRvdGFsZS0yMDIyMTAwNNIBAA?oc=5",
            "urlToImage": null,
            "publishedAt": "2022-10-04T17:58:21Z",
            "content": null
        },
        {
            "source": {
                "id": null,
                "name": "Ouest-France"
            },
            "author": "Ouest-France",
            "title": "Nantes. Après son rendez-vous avec le ministre de l'Intérieur, Johanna Rolland obtient 80 CRS - Ouest-France",
            "description": "La maire PS de Nantes avait demandé la création d’une force mobile permanente de 80 CRS. Le ministre de l’Intérieur lui en a donné l’assurance ce mardi 3 octobre, après un rendez-vous à Beauvau.",
            "url": "https://www.ouest-france.fr/pays-de-la-loire/nantes-44000/nantes-johanna-rolland-obtient-80-crs-628ba9aa-4408-11ed-9f8f-3a4ea2d19641",
            "urlToImage": "https://media.ouest-france.fr/v1/pictures/MjAyMjEwZmU4NTQyZTdiN2FjMzMwYTk5ZWRhMDljZmI1MzEyZjE?width=1260&height=708&focuspoint=50%2C25&cropresize=1&client_id=bpeditorial&sign=5c707593025e674f0fde09d6dd1d235eedf5156c90a9a32569315ad9a72a3ad1",
            "publishedAt": "2022-10-04T17:37:48Z",
            "content": "Johanna Rolland, la maire socialiste de Nantes, peut ressortir de Beauvau satisfaite. Sa demande a été entendue par le ministre de lIntérieur, Gérald Darmanin. Alors même que, cet après-midi, devant … [+865 chars]"
        },
        {
            "source": {
                "id": null,
                "name": "Francetvinfo.fr"
            },
            "author": null,
            "title": "Guerre en Ukraine : l'armée ukrainienne fait des \"progrès significatifs mais pas définitifs\", estime l'ambassadeur de France dans le pays - franceinfo",
            "description": "Les forces russes reculent dans le nord de la région de Kherson face à la contre-offensive ukrainienne. C'est ce que montre une carte militaire dévoilée mardi par le ministère russe de la Défense.",
            "url": "https://www.francetvinfo.fr/monde/europe/manifestations-en-ukraine/guerre-en-ukraine-l-armee-ukrainiens-fait-des-progres-significatifs-mais-pas-definitifs-estime-l-ambassadeur-de-france-dans-le-pays_5397523.html",
            "urlToImage": "https://www.francetvinfo.fr/pictures/d12oz_42e8VAwiz8hVN6Ga02vWA/1500x843/2022/10/04/phpBgd0DP.jpg",
            "publishedAt": "2022-10-04T17:27:37Z",
            "content": "Les forces russes reculent dans le nord de la région de Kherson face à la contre-offensive ukrainienne. C'est ce que montre une carte militaire dévoilée mardi par le ministère russe de la Défense. \"C… [+1335 chars]"
        },
        {
            "source": {
                "id": "le-monde",
                "name": "Le Monde"
            },
            "author": "Julien Lemaignen",
            "title": "« Le nouveau tir de missile par la Corée du Nord n'est pas un message pour le Japon, mais pour les Etats-Unis » - Le Monde",
            "description": "Pour Antoine Bondaz, de la Fondation pour la recherche stratégique, le test d’un missile à longue distance est moins significatif que le développement d’armes de courte portée.",
            "url": "https://www.lemonde.fr/international/article/2022/10/04/le-nouveau-tir-de-missile-par-la-coree-du-nord-n-est-pas-un-message-pour-le-japon-mais-pour-les-etats-unis_6144394_3210.html",
            "urlToImage": "https://img.lemde.fr/2022/10/04/0/0/5366/3577/1440/960/60/0/134d1da_5364546-01-06.jpg",
            "publishedAt": "2022-10-04T17:18:54Z",
            "content": "La Corée du Nord a procédé, pour la première fois depuis 2017, au tir dun missile balistique de portée intermédiaire au-dessus du Japon, mardi 4 octobre 2022. RICHARD A. BROOKS / AFP\r\nLe ciel du Japo… [+7784 chars]"
        },
        {
            "source": {
                "id": null,
                "name": "20 Minutes"
            },
            "author": "Caroline Vié",
            "title": "« Novembre » : Cédric Jimenez happé par l’enquête sur les attentats de 2015 - 20 Minutes",
            "description": "Le réalisateur de « Bac Nord » suit les enquêteurs qui ont traqué les terroristes après les attentats de 2015 dans « Novembre », au cinéma ce mercredi",
            "url": "https://www.20minutes.fr/cinema/4003146-20221004-novembre-cedric-jimenez-happe-enquete-attentats-2015",
            "urlToImage": "https://img.20mn.fr/BAyuRA6kSemm1nJNltmcSyk/1200x768_jean-dujardin-dans",
            "publishedAt": "2022-10-04T17:02:37Z",
            "content": "Cédric Jimenez choisit une façon très originale de parler des attentats de 13 novembre 2015. Dans Novembre, découvert hors compétition au Festival de Cannes 2022, le cinéaste prend le parti de suivre… [+2230 chars]"
        },
        {
            "source": {
                "id": null,
                "name": "La Tribune.fr"
            },
            "author": "Paul Marion",
            "title": "Royaume-Uni : Liz Truss « a réussi à aggraver la crise économique » - La Tribune.fr",
            "description": "Liz Truss est entrée au 10 Downing Street il y a un mois. Très attendue sur la crise économique, la Première ministre a dégainé une baisse massive d'impôts et un plafonnement des factures énergétiques. Mais l'absence de chiffrage budgétaire a ruiné la crédibi…",
            "url": "https://www.latribune.fr/economie/international/royaume-uni-liz-truss-a-reussi-a-aggraver-la-crise-economique-935379.html",
            "urlToImage": "https://static.latribune.fr/full_width/2026163/truss-et-kwarteng.jpg",
            "publishedAt": "2022-10-04T16:43:00Z",
            "content": "On prédisait à Liz Truss un automne chaotique. Les présages étaient en dessous de la réalité. A l'image de la mort soudaine d'Elisabeth II deux jours après leur rencontre, rien ne s'est passé comme p… [+5477 chars]"
        },
        {
            "source": {
                "id": null,
                "name": "Canalturf.com"
            },
            "author": null,
            "title": "Quinté PMU - Pronostic du PRIX GUILLAUME DE PRACOMTAL 4 oct. 2022 - Canal Turf",
            "description": "Découvrez le pronostic de la course PRIX GUILLAUME DE PRACOMTAL ainsi que les informations liées au Quinté+ PMU du 4 oct. 2022",
            "url": "https://www.canalturf.com/pronostics-PMU/2022-10-04/auteuil/286778_prix-guillaume-de-pracomtal.html",
            "urlToImage": "https://www.canalturf.com/interface/photosinfos/2022_5/MD_00208800-033-scoopdyga_IBAN_ROQUE.jpg",
            "publishedAt": "2022-10-04T16:02:01Z",
            "content": "Le pronostic Canalturf.com\r\nQuatre des quinze candidats au Prix Guillaume de Pracomtal, quinté de ce mardi, à Auteuil, ont pris part au quinté Prix Alain et Gilles de Goulaine, le 13 septembre sur le… [+5192 chars]"
        }
    ]
}