{
    "status": "ok",
    "totalResults": 34,
    "articles": [
        {
            "source": {
                "id": null,
                "name": "Lefigaro.fr"
            },
            "author": "Le Figaro avec AFP",
            "title": "Dix hommes jugés à Paris pour le braquage de la bijouterie Chopard en décembre 2015 - Le Figaro",
            "description": "Dix braqueurs présumés doivent être jugés à Paris à partir de mardi 4 janvier pour avoir participé, à des degrés divers, aux vols commis le 11...",
            "url": "https://www.lefigaro.fr/flash-actu/dix-hommes-juges-a-paris-pour-le-braquage-de-la-bijouterie-chopard-en-decembre-2015-20220103",
            "urlToImage": "https://i.f1g.fr/media/cms/616x347_crop/2022/01/03/aeba74fae0d0a7e458e9a7878ff4d10e6f1607931133579efb3d89987a4a8911.jpg",
            "publishedAt": "2022-01-03T09:18:47Z",
            "content": "Dix braqueurs présumés doivent être jugés à Paris à partir de mardi 4 janvier pour avoir participé, à des degrés divers, aux vols commis le 11 décembre 2015 chez le célèbre joaillier Chopard de la pl… [+3883 chars]"
        },
        {
            "source": {
                "id": null,
                "name": "Foot01.com"
            },
            "author": "Guillaume Conte",
            "title": "Messi fait une Neymar, le PSG peut pleurer - Foot01",
            "description": "Absent de la reprise du PSG, Lionel Messi va encore manquer des matchs. Son taux d'absentéisme se rapproche dangereusement de celui de Neymar. \r\nAnnoncé positif au Covid, Lionel Messi est resté en Argentine plus longtemps que prévu. L’attaquant du PSG…",
            "url": "https://www.foot01.com/equipe/paris/messi-fait-une-neymar-le-psg-peut-pleurer-394559",
            "urlToImage": "https://www.foot01.com/img/images/1200x/2022/Jan/03/messi-fait-une-neymar-le-psg-peut-pleurer-icon_dib-121221-11-147-331591.jpg",
            "publishedAt": "2022-01-03T09:00:55Z",
            "content": "Absent de la reprise du PSG, Lionel Messi va encore manquer des matchs. Son taux d'absentéisme se rapproche dangereusement de celui de Neymar. \r\nAnnoncé positif au Covid, Lionel Messi est resté en Ar… [+1794 chars]"
        },
        {
            "source": {
                "id": null,
                "name": "AlloCiné"
            },
            "author": "Loriane Cladec",
            "title": "Mort de Betty White à 99 ans, inoubliable \"Craquante\" et icone de la télé américaine - AlloCiné",
            "description": "L'actrice américaine Betty White est décédée le 31 décembre 2021 à 99 ans. Personnage lunaire de la série Les Craquantes, elle avait connu le succès grâce à cette comédie centrée sur des personnes âgé",
            "url": "https://www.allocine.fr/article/fichearticle_gen_carticle=18679666.html",
            "urlToImage": "https://fr.web.img4.acsta.net/newsv7/19/03/08/16/49/1513006.jpg",
            "publishedAt": "2022-01-03T08:55:00Z",
            "content": "L'actrice américaine Betty White est décédée le 31 décembre 2021 à 99 ans. Personnage lunaire de la série Les Craquantes, elle avait connu le succès grâce à cette comédie centrée sur des personnes âg… [+4058 chars]"
        },
        {
            "source": {
                "id": "le-monde",
                "name": "Le Monde"
            },
            "author": "Audrey Tonnelier",
            "title": "Covid-19 : le gouvernement confronté au retour des incertitudes économiques - Le Monde",
            "description": "La vague Omicron remet en cause le scénario de forte reprise et la fin du « quoi qu’il en coûte », à trois mois du scrutin présidentiel.",
            "url": "https://www.lemonde.fr/economie/article/2022/01/03/covid-19-le-gouvernement-confronte-au-retour-des-incertitudes-economiques_6108000_3234.html",
            "urlToImage": "https://img.lemde.fr/2022/01/03/421/0/5042/2521/1440/720/60/0/e13a879_955963888-771062.jpg",
            "publishedAt": "2022-01-03T08:38:38Z",
            "content": "Sur la photo, il pose, lair déterminé, une tasse à la main et en blouson daviateur. « Café chez nos amis restaurateurs au Pays basque. Nous sommes en contact régulier avec les professionnels (), pour… [+2928 chars]"
        },
        {
            "source": {
                "id": null,
                "name": "Www.lci.fr"
            },
            "author": "La rédaction de LCI avec AFP",
            "title": "Afrique du Sud : l'incendie dévastateur du Parlement maîtrisé, un suspect arrêté - LCI",
            "description": "INCENDIE - En Afrique du Sud, l'Assemblée nationale a été entièrement détruite par un violent incendie. Un homme de 49 ans, suspecté d'en être à l'origine, a été arrêté. Il comparaîtra devant la justice mardi.",
            "url": "https://www.lci.fr/international/afrique-du-sud-l-incendie-devastateur-du-parlement-au-cap-maitrise-un-suspect-arrete-2206103.html",
            "urlToImage": "https://photos.lci.fr/images/1280/720/incendie-assemblee-nationale-afrique-du-sud-76915b-0@1x.jpeg",
            "publishedAt": "2022-01-03T08:28:00Z",
            "content": "Le brasier a enfin été maîtrisé. L'incendie dévastateur du Parlement sud-africain au Cap, qui s'était déclaré tôt dimanche matin et a réduit l'enceinte de l'Assemblée nationale en cendres, a été circ… [+2423 chars]"
        },
        {
            "source": {
                "id": null,
                "name": "LaDepeche.fr"
            },
            "author": "Salomé D.",
            "title": "Musulmans et \"bonne année\" : les propos de Gims font polémique sur les réseaux sociaux - LaDepeche.fr",
            "description": "Le rappeur Gims ne veut pas qu'on lui souhaite la nouvelle année. Sur les réseaux sociaux, il publie des vidéos \"coup de gueule\", qui ont suscité la polémique.",
            "url": "https://www.ladepeche.fr/2022/01/03/musulmans-et-bonne-annee-les-propos-de-gims-font-polemique-sur-les-reseaux-sociaux-10024338.php",
            "urlToImage": "https://images.ladepeche.fr/api/v1/images/view/61d2b1f68fe56f796c42f1c4/large/image.jpg?v=1",
            "publishedAt": "2022-01-03T08:23:00Z",
            "content": "l'essentiel\r\n Le rappeur Gims ne veut pas qu'on lui souhaite la nouvelle année. Sur les réseaux sociaux, il publie des vidéos \"coup de gueule\", qui ont suscité la polémique.\r\n Gims n'est pas enclin à… [+2018 chars]"
        },
        {
            "source": {
                "id": null,
                "name": "BFMTV"
            },
            "author": null,
            "title": "Ligue 1: Bordeaux pousse pour le report du match face à l’OM - RMC Sport",
            "description": "Bordeaux devrait demander le report du match face à l’OM, prévu vendredi (21h, 20e journée de Ligue 1) en raison de cas toujours nombreux de contaminations au coronavirus.",
            "url": "https://rmcsport.bfmtv.com/football/ligue-1/ligue-1-bordeaux-pousse-pour-le-report-du-match-face-a-l-om_AV-202201030106.html",
            "urlToImage": "https://images.bfmtv.com/FVSVspGuAfA6Aa3csMGkQZbL_F4=/0x105:2048x1257/images/Vladimir-Petkovic-1202967.jpg",
            "publishedAt": "2022-01-03T08:14:15Z",
            "content": "Bordeaux devrait demander le report du match face à lOM, prévu vendredi (21h, 20e journée de Ligue 1) en raison de cas toujours nombreux de contaminations au coronavirus.\r\nLaventure de Bordeaux en Co… [+2208 chars]"
        },
        {
            "source": {
                "id": null,
                "name": "Ozap"
            },
            "author": "Benjamin Meffre",
            "title": "Audiences : \"Les tontons flingueurs\" leader devant \"Meurtres en eaux troubles\", TF1 seulement 3e, Arte proche du million - OZAP",
            "description": "Les audiences de la soirée du dimanche 2 janvier 2022.",
            "url": "https://www.ozap.com/actu/audiences-les-tontons-flingueurs-leader-devant-meurtres-en-eaux-troubles-tf1-seulement-3e-arte-au-million/612087",
            "urlToImage": "https://static1.ozap.com/articles/7/61/20/87/@/4659126--les-tontons-flingueurs-opengraph_1200-1.jpg",
            "publishedAt": "2022-01-03T08:09:00Z",
            "content": "Dimanche soir en prime time, France 2 est arrivée en tête des audiences avec le film français \"Les tontons flingueurs\". Ce classique du cinéma réalisé par Georges Lautner a amusé 3,50 millions de per… [+2030 chars]"
        },
        {
            "source": {
                "id": null,
                "name": "Francetvinfo.fr"
            },
            "author": null,
            "title": "A Marseille, l'appel de 500 médecins : \"Un seul vœu pour 2022 : vaccinez-vous !\" - franceinfo",
            "description": "Ces soignants de l'Assistance publique-hôpitaux de Marseille regrettent que la ville et sa région soient \"parmi les moins vaccinées de France\" et appellent leurs concitoyens à se faire massivement vacciner.",
            "url": "https://www.francetvinfo.fr/sante/maladie/coronavirus/vaccin/un-seul-voeu-pour-2022-vaccinez-vous-appellent-500-medecins-marseillais_4902589.html",
            "urlToImage": "https://www.francetvinfo.fr/pictures/nhAlJRxk-2z3_q1Abz6FJPMwVe4/1500x843/2022/01/03/phpa4qser.jpg",
            "publishedAt": "2022-01-03T08:08:05Z",
            "content": "Ces soignants de l'Assistance publique-hôpitaux de Marseille regrettent que la ville et sa région soient \"parmi les moins vaccinées de France\" et appellent leurs concitoyens à se faire massivement va… [+2139 chars]"
        },
        {
            "source": {
                "id": null,
                "name": "Francetvinfo.fr"
            },
            "author": null,
            "title": "Covid-19 : durées d'isolement, tests à l'école, masques pour les enfants... Voici tout ce qui change à partir - franceinfo",
            "description": "De nombreuses mesures annoncées ces derniers jours prennent effet lundi, jour de reprise et de rentrée après les congés de fin d'année.",
            "url": "https://www.francetvinfo.fr/sante/maladie/coronavirus/variant-delta/covid-19-durees-d-isolement-tests-a-l-ecole-masques-pour-les-enfants-voici-tout-ce-qui-change-au-3-janvier_4902557.html",
            "urlToImage": "https://www.francetvinfo.fr/pictures/vrznZf9dNnWhTpLxcMow5qWTwVo/1500x843/2022/01/03/php2odDPO.jpg",
            "publishedAt": "2022-01-03T07:53:41Z",
            "content": "De nombreuses mesures annoncées ces derniers jours prennent effet lundi, jour de reprise et de rentrée après les congés de fin d'année. Nouvelle année ou pas, la circulation des variants Delta et Omi… [+7222 chars]"
        },
        {
            "source": {
                "id": null,
                "name": "LaDepeche.fr"
            },
            "author": "Salomé D.",
            "title": "Covid-19 à l'école : communication par la presse, journées hybrides... pourquoi le protocole de Jean-Michel Bl - LaDepeche.fr",
            "description": "Le ministre de l'Education Jean-Michel Blanquer a dévoilé ce dimanche les nouveaux contours du protocole sanitaire qui s'appliquera dans les écoles à partir de ce lundi 3 janvier. Une annonce mal reçue chez les enseignants.",
            "url": "https://www.ladepeche.fr/2022/01/03/covid-19-a-lecole-communication-par-la-presse-journees-hybrides-pourquoi-le-protocole-de-jean-michel-blanquer-fait-polemique-10024302.php",
            "urlToImage": "https://images.ladepeche.fr/api/v1/images/view/61d2a761d286c215286873c3/large/image.jpg?v=1",
            "publishedAt": "2022-01-03T07:39:00Z",
            "content": "l'essentiel\r\n Le ministre de l'Education Jean-Michel Blanquer a dévoilé ce dimanche les nouveaux contours du protocole sanitaire qui s'appliquera dans les écoles à partir de ce lundi 3 janvier. Une a… [+3677 chars]"
        },
        {
            "source": {
                "id": null,
                "name": "Boursorama"
            },
            "author": null,
            "title": "CAC 40: rebond en vue pour la première séance de 2022 - Boursorama",
            "description": "(CercleFinance.com) - La Bourse de Paris devrait ouvrir en petite hausse lundi matin, laissant entrevoir un rebond après le recul de vendredi, même si les volumes s'annoncent toujours allégés, de nombreux investisseurs n'étant pas encore rentrés de leurs cong…",
            "url": "https://www.boursorama.com/bourse/actualites/cac-40-rebond-en-vue-pour-la-premiere-seance-de-2022-468127f3cb93e1a72234f71dfa2ab5c7",
            "urlToImage": "https://s.brsimg.com/static-000/cache/i/content/images/9/e/c/9ece80f4110d922a0f18d29a41d3a7ec-1200x800.jpg",
            "publishedAt": "2022-01-03T07:32:00Z",
            "content": "Le Palais Brongniart, ancien siège de la Bourse de Paris. (Crédit photo : - L. Grassin)\r\n(CercleFinance.com) - La Bourse de Paris devrait ouvrir en petite hausse lundi matin, laissant entrevoir un re… [+2852 chars]"
        },
        {
            "source": {
                "id": null,
                "name": "France Bleu"
            },
            "author": "Victor Tribot Laspière",
            "title": "Covid-19 : \"Il est probable que nous ayons tous acquis une forme d'immunité collective\", indique Olivier Véran - France Bleu",
            "description": "Invité de France Inter ce lundi, Olivier Véran, ministre de la Santé, a indiqué qu'il était \"probable\" que les Français aient acquis une forme d'immunité collective grâce à la vaccination et à la grande contagiosité du variant Omicron. Il précise qu'il s'agit…",
            "url": "https://www.francebleu.fr/infos/sante-sciences/covid-19-il-est-probable-que-nous-ayons-tous-acquis-une-forme-d-immunite-collective-indique-olivier-1641195027",
            "urlToImage": "https://cdn.radiofrance.fr/s3/cruiser-production/2022/01/a7815386-cc62-4561-b617-23b6cdca8667/870x489_000_9v76kc.jpg",
            "publishedAt": "2022-01-03T07:30:27Z",
            "content": "Alors qu'en ce lundi 3 janvier de rentrée scolaire, de nouvelles mesures entrent en vigueur pour lutter contre l'épidémie de Covid-19, Olivier Véran indique qu'il est \"probable que nous ayons tous ac… [+2736 chars]"
        },
        {
            "source": {
                "id": null,
                "name": "Onze Mondial"
            },
            "author": "Julien Pedebos",
            "title": "Chauvigny – OM : Marseille laisse un joli chèque, dernier match pour Mandanda avant un départ ? - Onze Mondial",
            "description": "Alors que l'OM a fait honneur à la tradition des professionnels face à Chauvigny, Steve Mandanda a peut-être disputé son dernier match à Marseille.",
            "url": "https://www.onzemondial.com/coupe-de-france/chauvigny-om-marseille-laisse-un-joli-cheque-dernier-match-pour-mandanda-avant-un-depart-740973",
            "urlToImage": "https://static.onzemondial.com/photo_article/740973/291119/1200-L-chauvigny-om-marseille-laisse-un-joli-chque-dernier-match-pour-mandanda-avant-un-dpart.jpg",
            "publishedAt": "2022-01-03T07:20:00Z",
            "content": "Zapping Onze Mondial Top 10 : Les plus fortes hausses de valeurs\r\nHier soir, pour le dernier match d'une longue journée de 16es de finale de Coupe de France, l'OM n'a pas tremblé une seconde face à C… [+1460 chars]"
        },
        {
            "source": {
                "id": null,
                "name": "Francetvinfo.fr"
            },
            "author": "Marie-Adélaïde Scigacz, Yann Thompson, Catherine Fournier",
            "title": "DIRECT. Covid-19 : le pass vaccinal arrive à l'Assemblée nationale - Franceinfo",
            "description": "Face à une épidémie de Covid-19 qui flambe, les députés examinent lundi le projet de loi transformant le pass sanitaire en pass vaccinal dont l'adoption ne fait aucun doute, malgré un climat tendu et l'hostilité de plusieurs partis.",
            "url": "https://www.francetvinfo.fr/sante/maladie/coronavirus/pass-sanitaire/direct-covid-19-le-pass-vaccinal-arrive-a-l-assemblee-nationale_4902543.html",
            "urlToImage": "https://www.francetvinfo.fr/image/760zjams0-a866/1500/843/26071539.jpg",
            "publishedAt": "2022-01-03T06:26:18Z",
            "content": "Retrouvez ici l'intégralité de notre live #COVID_19\r\n07h40 : \"Le gouvernement a fait le choix de la navigation à vue\", estime Valérie Pécresse, invitée ce matin de RTL. La candidate des Républicains … [+4934 chars]"
        },
        {
            "source": {
                "id": null,
                "name": "Francetvinfo.fr"
            },
            "author": null,
            "title": "Crise en Ukraine : Biden assure que les Etats-Unis \"répondront énergiquement\" à une invasion russe - franceinfo",
            "description": "Le président américain s'est entretenu dimanche avec son homologue ukrainien, pour réaffirmer le soutien de Washington à Kiev face à Moscou.",
            "url": "https://www.francetvinfo.fr/monde/europe/manifestations-en-ukraine/crise-en-ukraine-biden-assure-que-les-etats-unis-repondront-energiquement-a-une-invasion-russe_4902559.html",
            "urlToImage": "https://www.francetvinfo.fr/pictures/4-ufDrfxRSaA9p4hb9OzEWyxaDQ/1500x843/2022/01/03/php0Jn5my.jpg",
            "publishedAt": "2022-01-03T06:14:11Z",
            "content": "Le président américain s'est entretenu dimanche avec son homologue ukrainien, pour réaffirmer le soutien de Washington à Kiev face à Moscou.La guerre des mots continue. Le président américain Joe Bid… [+1772 chars]"
        },
        {
            "source": {
                "id": null,
                "name": "Midi Libre"
            },
            "author": "MIDI LIBRE",
            "title": "\"Flurona\" : quelle est cette double infection au Covid et à la grippe détectée pour la première fois en Israël - Midi Libre",
            "description": "Les experts étudient actuellement la combinaison des deux infections dans le but de savoir si cela pourrait ou non provoquer une maladie plus grave.",
            "url": "https://www.midilibre.fr/2022/01/02/flurona-quelle-est-cette-double-infection-au-covid-et-a-la-grippe-detectee-pour-la-premiere-fois-en-israel-10023629.php",
            "urlToImage": "https://images.midilibre.fr/api/v1/images/view/61d2093e8fe56f524d1485c8/large/image.jpg?v=1",
            "publishedAt": "2022-01-03T06:14:00Z",
            "content": "Les experts étudient actuellement la combinaison des deux infections dans le but de savoir si cela pourrait ou non provoquer une maladie plus grave.\r\n Le premier cas de \"Flurona\" a été identifié. Cet… [+1139 chars]"
        },
        {
            "source": {
                "id": null,
                "name": "Midi Libre"
            },
            "author": "Midi Libre",
            "title": "Soldes d'hiver 2022 : à quelle date débutent les bonnes affaires cette année ? - Midi Libre",
            "description": "Sauf contre ordre du gouvernement en raison de la crise sanitaire, ce qui avait été le cas en 2021, les soldes d'hiver 2022 doivent se tenir du 12 janvier au 8 février dans la plupart des départements français.",
            "url": "https://www.midilibre.fr/2022/01/03/soldes-dhiver-2022-a-quelle-date-debutent-les-bonnes-affaires-cette-annee-10024266.php",
            "urlToImage": "https://images.midilibre.fr/api/v1/images/view/61d293f43e454663b448c3d6/large/image.jpg?v=1",
            "publishedAt": "2022-01-03T06:13:00Z",
            "content": "Sauf contre ordre du gouvernement en raison de la crise sanitaire, ce qui avait été le cas en 2021, les soldes d'hiver 2022 doivent se tenir du 12 janvier au 8 février dans la plupart des département… [+1113 chars]"
        },
        {
            "source": {
                "id": null,
                "name": "Le 10 Sport"
            },
            "author": "Th.B.",
            "title": "Mercato - PSG : Pochettino annonce la couleur pour l’avenir de Mbappé ! - Le 10 Sport",
            "description": "Alors qu’une prolongation de contrat n’a toujours pas eu lieu dans le feuilleton Kylian Mbappé, qui pourrait trouver son épilogue dans une signature en tant qu’agent libre en juin prochain, Mauricio…",
            "url": "https://le10sport.com/football/mercato/mercato-psg-pochettino-annonce-la-couleur-pour-lavenir-de-mbappe-582016",
            "urlToImage": "https://le10static.com/img/master/0000/0019/199834.jpeg",
            "publishedAt": "2022-01-03T05:45:00Z",
            "content": "Publié le 3 janvier 2022 à 6h45 par Th.B. Alors quune prolongation de contrat na toujours pas eu lieu dans le feuilleton Kylian Mbappé, qui pourrait trouver son épilogue dans une signature en tant qu… [+1077 chars]"
        },
        {
            "source": {
                "id": null,
                "name": "Orange.fr"
            },
            "author": "https://www.facebook.com/orangeactufr",
            "title": "Colorado: deux personnes toujours disparues après des incendies dévastateurs - Actu Orange",
            "description": "Deux personnes sont toujours portées disparues et une a été retrouvée vivante après des incendies qui ont détruit près d'un millier de maisons jeudi dans l'Etat américain du Colorado, ont indiqué les autorités dimanche.",
            "url": "https://actu.orange.fr/societe/fait-divers/colorado-deux-personnes-toujours-disparues-apres-des-incendies-devastateurs-CNT000001IcdGh.html",
            "urlToImage": "http://media2.woopic.com/api/v1/images/661%2Fafp-news%2Fdb4%2F6d1%2F78f4ced23328402520d7319c9c%2Fcolorado-deux-personnes-toujours-disparues-apres-des-incendies-devastateurs%7C000_9VF3CA-highDef.jpg?format=470x264&facedetect=1&quality=85",
            "publishedAt": "2022-01-03T05:08:51Z",
            "content": "AFP, publié le lundi 03 janvier 2022 à 06h08\r\nDeux personnes sont toujours portées disparues et une a été retrouvée vivante après des incendies qui ont détruit près d'un millier de maisons jeudi dans… [+1981 chars]"
        }
    ]
}