{
    "status": "ok",
    "totalResults": 30,
    "articles": [
        {
            "source": {
                "id": null,
                "name": "Hkepc.com"
            },
            "author": "https://www.facebook.com/pinghkepc",
            "title": "高性價比、電競妖板!! ASROCK B550 PG Riptide 主機板 - 電腦領域",
            "description": "ASROCK 推出全新 B550 PG Riptide 主機板，是為 Phantom Gaming 系列中的新型號，主打高性價比和具備電競功能的主機板，採用 10 相 50A DrMOS 供電設計，可為 Ryzen 5000 CPU 提供不錯的性能輸出，加入針對遊戲網絡最佳化的 Killer E31",
            "url": "https://www.hkepc.com/20435/%E9%AB%98%E6%80%A7%E5%83%B9%E6%AF%94%E9%9B%BB%E7%AB%B6%E5%A6%96%E6%9D%BF__ASROCK_B550_PG_Riptide_%E4%B8%BB%E6%A9%9F%E6%9D%BF",
            "urlToImage": "https://file1.hkepc.net/2021/06/source/2318214909502634915.jpg",
            "publishedAt": "2021-06-23T10:13:27Z",
            "content": "ASROCK B550 PG Riptide \r\nASROCK B550 PG Riptide \r\nASROCK B550 PG Riptide 8 + 2 50A DrMOS CPU PCIe 4.0 2 M.2 SSD Killer E3100G 2.5G Lightning Gaming Ports DDR4-4933+ \r\nASROCK B550 PG Riptide ATX Form … [+4651 chars]"
        },
        {
            "source": {
                "id": null,
                "name": "Hket.com"
            },
            "author": "香港經濟日報HKET",
            "title": "【美股動態】關注歐美PMI數據道指期貨升47點納指期貨升0.1%（不斷更新） - 香港經濟日報- 即時新聞頻道- 即市財經- 股市 - 香港經濟日報 - 即時新聞",
            "description": "聯儲局主席鮑威爾稱儲局不會先發制人加息，美股上升，道指隔晚升68點。美股期貨於周三亞洲時段續向好，道指期貨升82點或0.2%；標指期貨升6點或0.2%；納指期貨升34點或0.2%。美國今日將公布6月M",
            "url": "https://inews.hket.com/article/2986968/【美股動態】關注歐美PMI數據　道指期貨升47點　納指期貨升0.1-（不斷更新）",
            "urlToImage": "https://static01-proxy.hket.com/res/v3/image/content/2985000/2986968/usstock_1024_1024_1024.jpg",
            "publishedAt": "2021-06-23T09:18:00Z",
            "content": "68820.2%60.2%340.2%6Markit5\r\n1716471100.1%\r\n1241820.2%60.2%340.2%\r\n11153340002000\r\n1000Krispy Kreme3105\r\n1000\r\n0805Uber13%\r\n==622==\r\n2070 2%\r\n33945684246210.5%142531110.879%\r\n328,81432630GameStop5001… [+1462 chars]"
        },
        {
            "source": {
                "id": null,
                "name": "Sina.com.tw"
            },
            "author": "北京新浪網",
            "title": "橙色海洋！F1奧地利站將迎14萬荷蘭觀眾-體育新聞 - 臺灣新浪網",
            "description": "接下來的兩周，一級方程式賽車將在奧地利的紅牛環賽道上進行兩場背靠背比賽。赫爾穆特·馬爾科已經明確表示，紅牛的目標是讓第二場比賽坐滿觀眾。 「我們將允許1....",
            "url": "https://news.sina.com.tw/article/20210623/38982518.html",
            "urlToImage": "https://newsimgs.sina.tw/article/images/news-16244389119706.png",
            "publishedAt": "2021-06-23T09:00:41Z",
            "content": null
        },
        {
            "source": {
                "id": null,
                "name": "Pcmarket.com.hk"
            },
            "author": null,
            "title": "WhatsApp 終不會支援多部流動裝置登入同一帳號| PCM - PCM",
            "description": "根據 Android Police 引述 WABetaInfo 的最新消息表示，WhatsApp 雖然會加入多裝置登入的功能，但原來只會支援 WhatsApp Web 網頁版、WhatsApp Desktop 桌面程式及 Facebook Portal 智能屏幕裝置，而不是開放予多台流動裝置可以共同使用同一 WhatsApp 帳號。",
            "url": "https://www.pcmarket.com.hk/whatsapp-will-not-support-multiple-mobile-devices-to-login-the-same-account/",
            "urlToImage": "https://plugmedia-wp-uploads.s3.ap-southeast-1.amazonaws.com/wp-content/uploads/2020/06/6.jpg",
            "publishedAt": "2021-06-23T07:52:16Z",
            "content": "WhatsApp WhatsApp Android Police WABetaInfo WhatsApp WhatsApp Web WhatsApp Desktop Facebook Portal WhatsApp \r\nWABetaInfo WhatsApp WhatsApp WhatsApp"
        },
        {
            "source": {
                "id": null,
                "name": "Appledaily.com"
            },
            "author": "蘋果新聞網",
            "title": "妨礙中籃爭議！NBA裁判報告認證艾頓空接灌籃絕殺「合法」 ｜ 蘋果新聞網｜ 蘋果日報 - 台灣蘋果日報",
            "description": "西區決賽第2戰太陽主場迎戰快艇，比賽最後1分鐘居然打了33分鐘，最終太陽靠著中鋒艾頓(Deandre Ayton)的空中接力灌籃絕殺，以104比103奪勝，取得2比0領先，但艾頓的這記致勝空中接力灌籃是否為妨礙中籃也引起熱議，聯盟賽後也立即以「裁判報告」提出解釋。 經過比賽重...",
            "url": "https://tw.appledaily.com/sports/20210623/FLQVL5IXFJBRRG3VXC5ZEJ3CJI/",
            "urlToImage": "https://tw.appledaily.com/resizer/5DJSKz9Q02_qG1mM3IckyeQwPHc=/1855x1314/filters:quality(100)/cloudfront-ap-northeast-1.images.arcpublishing.com/appledaily/RDVU2YBUGFHPNIPR3Z6KOL7WGA.jpg",
            "publishedAt": "2021-06-23T07:50:56Z",
            "content": "2133(Deandre Ayton)10410320\r\n1NBANBA1\r\n0.90.20.7"
        },
        {
            "source": {
                "id": null,
                "name": "Hk01.com"
            },
            "author": "李恩慈",
            "title": "機場工作居大埔男染疫帶變種病毒大埔區多個屋苑須強制檢測 - 香港01",
            "description": "本港新冠肺炎疫情反覆，衞生防護中心今日（23日）公布，新增兩宗輸入個案，包括一名外傭及一名未曾「落地」的船員。不過，一名居於大埔、在機場工",
            "url": "https://www.hk01.com/社會新聞/641715/機場工作居大埔男染疫-帶變種病毒-大埔區多個屋苑須強制檢測",
            "urlToImage": "https://cdn.hk01.com/di/media/images/dw/20210623/484414978539917312259168.jpeg/BaC2n6zuQnVDhbMUhP0dllQfR0vSZIAABJ6c3wSenN8",
            "publishedAt": "2021-06-23T07:43:07Z",
            "content": "2021-06-23 18:25\r\n vs \r\n34#11898619CX278021L452R\r\n49#1189922\r\n55\r\n20216106232625621623\r\nGoogle ChromeMozilla FirefoxMicrosoft Edge Safari"
        },
        {
            "source": {
                "id": null,
                "name": "Rthk.hk"
            },
            "author": null,
            "title": "陳振英認為滙豐銀行修改條款與國安法無關- RTHK - 香港電台",
            "description": "滙豐銀行昨日發出有關香港客戶在海外使用網上或流動理財服務的通知，引起關注。金融界立法會議員陳振英說，本港一些大型銀行的條款與滙豐銀行一樣，只是公眾以往未有留意。但他相信，本港客戶到外地旅遊或公幹可繼續使用網上理財服務。他指出，有關條款早在《香港國安法》生效前已存在，認為條款修改的做法與國安法無關。...",
            "url": "https://news.rthk.hk/rthk/ch/component/k2/1597272-20210623.htm",
            "urlToImage": "https://newsstatic.rthk.hk/images/mfile_1597272_1_L_20210623145443.jpg",
            "publishedAt": "2021-06-23T05:45:00Z",
            "content": null
        },
        {
            "source": {
                "id": null,
                "name": "Mingpao.com"
            },
            "author": null,
            "title": "陳凱琳30歲生日酒店度假慶祝鄭嘉穎Sweet爆唱生日歌- 20210623 - SHOWBIZ - 明報OL網",
            "description": "陳凱琳（Grace）今天（6月23日）30歲生日，一如所願與丈夫鄭嘉穎及兩個寶貝仔到酒店Staycation慶祝。她在社交平台上載一家四口在酒店內的度假片，包括夫婦二人帶住大仔Rafael及細仔Yannick在酒店泳池玩水、嘉穎與Rafael玩耍、嘉穎為她唱生日歌，以及她餵嘉穎吃東西的片段，既溫馨又甜蜜﹗",
            "url": "https://ol.mingpao.com/ldy/showbiz/latest/20210623/1624424604293/陳凱琳30歲生日酒店度假慶祝-鄭嘉穎sweet爆唱生日歌",
            "urlToImage": "https://fs.mingpao.com/ldy/20210623/s00009/2902303ac5e8b813d2f2aece1ee92024.jpg",
            "publishedAt": "2021-06-23T05:42:48Z",
            "content": "Grace62330StaycationRafaelYannickRafael\r\nGrace30Derek"
        },
        {
            "source": {
                "id": null,
                "name": "Hk.on.cc"
            },
            "author": "",
            "title": "教師買《蘋果》回校派發楊潤雄：校園不應有政治活動 - on.cc東網",
            "description": "本港屢次發生有教師將政治帶入學堂的情況，有議員今日(23日)提出質詢，指部分教師向學生灌輸歪曲觀念，教育局應加強對教師的",
            "url": "https://hk.on.cc/hk/bkn/cnt/news/20210623/bkn-20210623120214960-0623_00822_001.html",
            "urlToImage": "https://hk.on.cc/hk/bkn/cnt/news/20210623/photo/bkn-20210623120214960-0623_00822_001_01b.jpg?20210623142829",
            "publishedAt": "2021-06-23T04:44:20Z",
            "content": null
        },
        {
            "source": {
                "id": null,
                "name": "Rthk.hk"
            },
            "author": null,
            "title": "首宗國安法案控方引劉智鵬指「光時」口號有港獨意思- RTHK - 香港電台",
            "description": "首宗被控違反《香港國安法》的案件今早開審，被告唐英傑否認煽動他人分裂國家罪、恐怖活動罪及一項危險駕駛致他人身體受嚴重傷害的交替控罪。 署理副刑事檢控專員周天行在開案陳詞提到，唐英傑自2019年6月起都留在香港，由翌年4月至到國安法實施，傳媒都有廣泛報道，唐英傑是知悉有關法例。 周天行又引用控方證人、...",
            "url": "https://news.rthk.hk/rthk/ch/component/k2/1597259-20210623.htm",
            "urlToImage": "https://newsstatic.rthk.hk/images/mfile_1597259_1_L_20210623145340.jpg",
            "publishedAt": "2021-06-23T04:43:00Z",
            "content": null
        },
        {
            "source": {
                "id": null,
                "name": "Rthk.hk"
            },
            "author": null,
            "title": "何栢良：縮短英國抵港檢疫至7日或令本港清零一舖清袋- RTHK - 香港電台",
            "description": "港大感染及傳染病中心總監何栢良表示，英國確診新型肺炎的個案有上升趨勢，本港沒有理由縮短由英國返港、已接種疫苗人士的酒店檢疫日數至7日，又認為應該將英國由現時的B組高風險指明地區，提升至A2甚高風險指明地區。 何栢良在一個電台節目說，根據英國數據，5月共有7萬6千宗確診個案、但在6月首20日就有15萬...",
            "url": "https://news.rthk.hk/rthk/ch/component/k2/1597236-20210623.htm",
            "urlToImage": "https://newsstatic.rthk.hk/images/mfile_1597236_1_L_20210623114305.jpg",
            "publishedAt": "2021-06-23T03:28:00Z",
            "content": null
        },
        {
            "source": {
                "id": null,
                "name": "Hk01.com"
            },
            "author": "許祺安",
            "title": "習近平與神舟十二號航天員「天地通話」：在北京等候你們凱旋 - 香港01",
            "description": "國家主席習近平周三（23日）上午到北京航天飛行控制中心，於9時30分左右同神舟十二號航天員聶海勝、劉伯明、湯洪波「天地通話」。 ​​​三名航天員上",
            "url": "https://www.hk01.com/即時中國/641529/習近平與神舟十二號航天員-天地通話-在北京等候你們凱旋",
            "urlToImage": "https://cdn.hk01.com/di/media/images/dw/20210623/484308511962959872189247.jpeg/3aoYl-hI-Rw_DY9kgCdgvqCHri-kjjJ2t2QUsLdkFLA?v=w1280r16_9",
            "publishedAt": "2021-06-23T03:17:19Z",
            "content": "2021-06-23 11:17\r\n3\r\n3\r\n3\r\n19649201461998120051011201367201912\r\n19669199812008911201912\r\n19751020105201912"
        },
        {
            "source": {
                "id": "google-news",
                "name": "Google News"
            },
            "author": null,
            "title": "【全球大視野上集】大陸新任駐美大使面對華府強硬外交挑戰@全球大視野20210622 - 全球大視野",
            "description": null,
            "url": "https://news.google.com/__i/rss/rd/articles/CBMiK2h0dHBzOi8vd3d3LnlvdXR1YmUuY29tL3dhdGNoP3Y9end1M0xCUTF4YUHSAQA?oc=5",
            "urlToImage": null,
            "publishedAt": "2021-06-23T03:00:17Z",
            "content": null
        },
        {
            "source": {
                "id": null,
                "name": "Ulifestyle.com.hk"
            },
            "author": null,
            "title": "聲夢傳奇｜文凱婷晉級7強戰資格備受外界質疑網民：火雞同Felix唱功都喺佢之上- 晴報- 娛樂- 中港台 - 晴報 Sky Post",
            "description": "無綫舉辦的歌唱比賽節目《聲夢傳奇》至今已播出10集，來到第六輪比賽，4位學員將與1位歌手導師合唱自選歌曲，陣容有林智樂（Felix）與林奕匡、林君蓮（Kaitlyn）與泳兒、冼靖峰（Archie）與馮",
            "url": "https://skypost.ulifestyle.com.hk/article/2988345/聲夢傳奇｜文凱婷晉級7強戰資格備受外界質疑 網民：火雞同Felix唱功都喺佢之上",
            "urlToImage": "https://resource01-proxy.ulifestyle.com.hk/res/v3/image/content/2985000/2988345/888888_1024.jpeg",
            "publishedAt": "2021-06-23T01:40:45Z",
            "content": "1041FelixKaitlynArchieAeren\r\n{{hket:inline-image name=\"02.jpg\"}}{{/hket:inline-image}}\r\nFelixBuskingFelixFelixFelix11foul\r\nAerenAerenshowAeren13\r\n↓↓\r\n<ul><li>{{hket:inline-image name=\"1.jpg\"}}{{/hket… [+1767 chars]"
        },
        {
            "source": {
                "id": null,
                "name": "Appledaily.com"
            },
            "author": "蘋果新聞網",
            "title": "打壓港蘋｜香港《蘋果日報》宣布網站午夜起停止運作明天出版最後一份報紙｜ 蘋果新聞網｜ 蘋果日報 - 台灣蘋果日報",
            "description": "香港《蘋果日報》因港府打壓、拘捕高層並凍結相關銀行帳戶與資金，被迫停止營運，包括香港《蘋果日報》紙本、新聞網站都將停止運作。 香港警務處國家安全處繼本月17日搜查香港《蘋果日報》大樓，拘捕壹傳媒集團兩名高層及3名新聞工作者，消息指今（23日）晨再拘捕筆名為「李平」的《蘋果日報...",
            "url": "https://tw.appledaily.com/international/20210623/ETNCX4WE45G33NX4F42CZNBE44/",
            "urlToImage": "https://tw.appledaily.com/resizer/CTvSxVbzXbb3rrksZGvsHm2aLHo=/1920x1080/filters:quality(100)/cloudfront-ap-northeast-1.images.arcpublishing.com/appledaily/N5YJSMNKNBBXFOPHPVMIK2B3BM.jpg",
            "publishedAt": "2021-06-23T01:32:45Z",
            "content": null
        },
        {
            "source": {
                "id": null,
                "name": "Hk01.com"
            },
            "author": "聯合新聞網",
            "title": "新冠疫苗︱台醫生提醒打針前後3種嚴禁行為接種前不要吃什麼？ - 香港01",
            "description": "台灣本土確診數逐步下降，各縣市也全面開打疫苗，希望盡快提升疫苗接種率，防堵疫情再度擴大。但近日卻傳出多起民眾、長者接種後猝死、身體不適的個",
            "url": "https://www.hk01.com/台灣新聞/641170/新冠疫苗-台醫生提醒打針前後3種嚴禁行為-接種前不要吃什麼",
            "urlToImage": "https://cdn.hk01.com/di/media/images/dw/20210622/483996875314171904960254.jpeg/_ZMsI00Jdpq2PlH3gsGKTVS6CrrP1sE8mO_kLZjv5C0?v=w1280r16_9",
            "publishedAt": "2021-06-23T00:00:00Z",
            "content": null
        },
        {
            "source": {
                "id": null,
                "name": "Now.com"
            },
            "author": "Now 新聞",
            "title": "聯合國人權理事會多國憂慮香港自由惡化外交部：逾90國支持中國發出正義呼聲 - now 新聞",
            "description": "【Now新聞台】逾40個國家在聯合國人權理事會上發表聯合聲明，表示憂慮香港的自由惡化。白俄羅斯則代表65個國家發言，反對以人權為藉口干涉中國內政。",
            "url": "https://news.now.com/home/local/player?newsId=439590",
            "urlToImage": "https://images-news.now.com/newsimage/NewsImage/2021-06-23-10-15-13UQvyrDR3.jpg",
            "publishedAt": "2021-06-22T23:51:43Z",
            "content": null
        },
        {
            "source": {
                "id": null,
                "name": "Rthk.hk"
            },
            "author": null,
            "title": "英格蘭小勝捷克首名出線克羅地亞次名晉級- RTHK - 香港電台",
            "description": "歐洲國家盃D組，英格蘭1比0小勝捷克，三戰得7分首名出線。 英格蘭開賽12分鐘，由基亞利殊左路助攻予史達寧門前頭鎚建功，是隊中暫時唯一在今屆賽事取得入波的球員，另一名射手哈利卡尼今場繼續表現一般。佐敦軒達臣尾段一度將個波送入網，但被判越位在先。 克羅地亞憑尼高拉華錫的入球、加上隊長摩迪下半場一傳一射...",
            "url": "https://news.rthk.hk/rthk/ch/component/k2/1597195-20210623.htm",
            "urlToImage": "https://newsstatic.rthk.hk/images/mfile_1597195_1_L_20210623071027.jpg",
            "publishedAt": "2021-06-22T23:10:00Z",
            "content": null
        },
        {
            "source": {
                "id": null,
                "name": "Mingpao.com"
            },
            "author": "https://www.facebook.com/mingpaoinews",
            "title": "劉銳紹：政治上自我完善的意願和能力 中共建黨百年隨想之二- 20210623 - 觀點 - 明報新聞網",
            "description": "【明報文章】上周談了中共建黨和執政後在經濟、外交、綜合國力等方面的變化，另一個各方更關注的問題，就是它對內的管治模式和效果了。對此，我有4點隨想。",
            "url": "https://news.mingpao.com/pns/%e8%a7%80%e9%bb%9e/article/20210623/s00012/1624385884490/%e5%8a%89%e9%8a%b3%e7%b4%b9-%e6%94%bf%e6%b2%bb%e4%b8%8a%e8%87%aa%e6%88%91%e5%ae%8c%e5%96%84%e7%9a%84%e6%84%8f%e9%a1%98%e5%92%8c%e8%83%bd%e5%8a%9b%e2%94%80%e2%94%80%e4%b8%ad%e5%85%b1%e5%bb%ba%e9%bb%a8%e7%99%be%e5%b9%b4%e9%9a%a8%e6%83%b3%e4%b9%8b%e4%ba%8c",
            "urlToImage": "https://fs.mingpao.com/image/mingpao_logo_200.png",
            "publishedAt": "2021-06-22T21:03:04Z",
            "content": "4\r\n1\r\nlike\r\n2\r\n1980\r\n1987\r\n40302010\r\n3\r\n4\r\n[]"
        },
        {
            "source": {
                "id": null,
                "name": "Hket.com"
            },
            "author": "香港經濟日報HKET",
            "title": "【恒指夜期＋ADR】夜期收市升131點騰訊ADR靠穩北水吸資9億買吉利20億再沽騰訊（不斷更新） - 香港經濟日報- 即時新聞頻道- 即市財經- 股市 - 香港經濟日報 - 即時新聞",
            "description": "恒指夜期收市升131點，收報28324點，儲局主席鮑威爾維持通脹上升的力量是暫時的，並對復甦樂觀，紓緩市場對加息步伐的憂慮，在講話期間納指再創新高，納指收市升0.8%，道指升68點，騰訊ADR折算收報",
            "url": "https://inews.hket.com/article/2987728/【恒指夜期＋ADR】夜期收市升131點　騰訊ADR靠穩　北水吸資9億買吉利　20億再沽騰訊（不斷更新）",
            "urlToImage": "https://static01-proxy.hket.com/res/v3/image/content/2985000/2987728/SOUTHBOUND_1024.jpg",
            "publishedAt": "2021-06-22T20:46:00Z",
            "content": "131283240.8%68ADR575.610.4%\r\nADR\r\n<table><tr><td>ADR</td><td></td><td></td></tr><tr><td>ADR</td><td>45.70</td><td>-0.1%</td></tr><tr><td></td><td>182.02</td><td>+1.7%</td></tr><tr><td>ADR</td><td>575… [+2488 chars]"
        }
    ]
}