{
    "status": "ok",
    "totalResults": 34,
    "articles": [
        {
            "source": {
                "id": null,
                "name": "YouTube"
            },
            "author": null,
            "title": "미, 배터리 원료에 4조원 투자…핵심광물 공급망 강화 / JTBC 아침& - JTBC News",
            "description": "미국 정부가 전기차 핵심인 배터리 원료에 대한 미국 내 생산을 늘리기 위해 우리 돈 약 4조 원을 투자하겠다는 계획을 발표했습니다. 백악관은 현재 중국이 핵심광물 공급망의 많은 부분을 통제하고 있다면서 여기에서 벗어나야 한다고 강조했습니다.▶ 기사 전문 https://news.jt...",
            "url": "https://www.youtube.com/watch?v=_Q0xPI9-84E",
            "urlToImage": "https://i.ytimg.com/vi/_Q0xPI9-84E/maxresdefault.jpg",
            "publishedAt": "2022-10-19T23:35:28Z",
            "content": null
        },
        {
            "source": {
                "id": null,
                "name": "Kormedi.com"
            },
            "author": "정희은 기자",
            "title": "﻿목감기 통증?... 가라앉히는 방법 4가지 - 코메디닷컴",
            "description": "올해 가을철 감기 환자가 급증하고 있다. 감기엔 여러 종류가 있지만 목이 붓고 따끔거리는 통증은 짜증을 자아낸다. 집에서 아픈 목을 치료하는 방법은 없을까. 영국의 한 연구에 따르면 흔히 목감기로 불리는 인후염에 걸려 병원을 찾은 사람들에게 항생제를 처방할 필요가 없는 것으로 나타났다. 목이 아픈 원인으로는 일반 감기나 알레르기, 건조한 공기, 바이러스 등이 꼽힌다. 건강 정보 사이트 ‘멘스 헬스(Men’s Health)’가 목이 아플",
            "url": "https://kormedi.com/1535577/목감기-통증-가라앉히는-방법-4가지/",
            "urlToImage": "https://kormedi.com/wp-content/uploads/2022/10/ck-cb2000003906-l-700x369.jpg",
            "publishedAt": "2022-10-19T23:26:49Z",
            "content": ": 214-87-97051 | : 00292 | : 2006.11.30 | : | : 02-2052-8200~2: 324 7 | : 2006.11.30 | : | : \r\n© KoreaMedicare All right reserved."
        },
        {
            "source": {
                "id": null,
                "name": "Kormedi.com"
            },
            "author": "김영섭 기자",
            "title": "상태 나쁘고 나이 든 암환자…진단 전 ‘이런 증상’ 보여 - 코메디닷컴",
            "description": "암 진행 상태(예후)가 나쁜 노인 암 환자는 암 진단 이전에 보행 장애 등 각종 증상에 시달리는 것으로 나타났다. 미국 캘리포니아대 샌프란시스코캠퍼스(UCSF) 연구팀이 노인의료보험(메디케어) 1998~2016년 청구와 관련된 미국 건강은퇴연구(HRS) 데이터를 이용해 분석한 결과다.연구팀은 예후가 나빠 1년도 채 살기 힘든 암으로 진단받은 65세 이상 참가자 2105명(평균 연령 76세, 여성 53%)를 분석했다. 참가자 가운데 34%는 폐암",
            "url": "https://kormedi.com/1535635/1535635/",
            "urlToImage": "https://kormedi.com/wp-content/uploads/2022/10/gettyimages-1224952446-700x467.jpg",
            "publishedAt": "2022-10-19T23:16:00Z",
            "content": ". , .[=]\r\n() .  (UCSF) () 1998~2016 (HRS) .\r\n 1 65 2105( 76, 53%) . 34% , 21% 9.6.\r\n 65% , 36% 2 , 32% . , , , .\r\n 49% , 35% . 85 . 65~74 , .\r\n UCSF (·) 1 , . .\r\n (The epidemiology of preexisting ger… [+136 chars]"
        },
        {
            "source": {
                "id": null,
                "name": "Hankyung.com"
            },
            "author": null,
            "title": "'정우영 45분' 프라이부르크, 2부 팀에 연장승…포칼 16강 진출 - 한국경제",
            "description": "'정우영 45분' 프라이부르크, 2부 팀에 연장승…포칼 16강 진출, 문화스포츠",
            "url": "https://www.hankyung.com/sports/article/202210200316Y",
            "urlToImage": "https://img.hankyung.com/photo/202210/ZK.31572564.1.jpg",
            "publishedAt": "2022-10-19T23:09:06Z",
            "content": "(21) (21) . 20 2022-2023 10 0-1 . 24 . 5 . 1 3 1 5(1-4 ) . 1 ' ' 9 A . , 30 6 . . 4 3, 89% . 1 . 30 . 4 ."
        },
        {
            "source": {
                "id": null,
                "name": "Mt.co.kr"
            },
            "author": "채태병",
            "title": "'암투병' 서정희, 서세원과 이혼·폭행 언급…\"꼬리표 받아들여\" - 머니투데이",
            "description": "유방암 투병 중인 방송인 서정희(60)가 전 남편 서세원에 대해 언급했다.서정희는 20일 자신의 인스타그램에 과거 촬영한 화보 사진을 공개하며 &quot;궁금한 이야기를...",
            "url": "https://news.mt.co.kr/mtview.php?no=2022102007204663944",
            "urlToImage": "https://thumb.mt.co.kr/21/2022/10/2022102007204663944_1.jpg",
            "publishedAt": "2022-10-19T23:01:09Z",
            "content": "[] ()[]2020.11.04~2023.11.03"
        },
        {
            "source": {
                "id": null,
                "name": "YouTube"
            },
            "author": null,
            "title": "'푸이그 3점 선제포' 키움, 준PO 3차전 완승 \"PO 1승 남았다\" / YTN - YTN",
            "description": "프로야구 준플레이오프 3차전에서 타선이 폭발한 키움이 kt를 완파하고 시리즈 전적 2승 1패를 기록했습니다키움은 1회 푸이그의 선제 3점포를 시작으로 kt 선발 고영표를 3회에 일찌감치 강판시키면서 대량 득점에 성공해 9대 2 완승을 거뒀습니다키움 선발 애플러는 5이닝 1실점으로 ...",
            "url": "https://www.youtube.com/watch?v=9LuBzAUCu8w",
            "urlToImage": "https://i.ytimg.com/vi/9LuBzAUCu8w/maxresdefault.jpg",
            "publishedAt": "2022-10-19T22:42:25Z",
            "content": null
        },
        {
            "source": {
                "id": null,
                "name": "Mt.co.kr"
            },
            "author": "차유채",
            "title": "'179억 파산' 심형래, 오션뷰 숙소 공개…럭셔리 샹들리에까지 - 머니투데이",
            "description": "코미디언 겸 영화감독 심형래가 호화로운 숙소를 공개했다.19일 방송된 TV조선 &quot;퍼펙트 라이프&quot; 113회에서는 &quot;원조 영구&quot; 심형래의...",
            "url": "https://news.mt.co.kr/mtview.php?no=2022102007122463381",
            "urlToImage": "https://thumb.mt.co.kr/21/2022/10/2022102007122463381_1.jpg",
            "publishedAt": "2022-10-19T22:31:36Z",
            "content": "[] ()[]2020.11.04~2023.11.03"
        },
        {
            "source": {
                "id": null,
                "name": "Hani.co.kr"
            },
            "author": null,
            "title": "[단독] SPC 빵공장, 사고 목격 노동자들 다음날 '정상출근' 시켰다 - 한겨레",
            "description": "“동료 노동자 트라우마 고려 안 하나” 비판",
            "url": "https://www.hani.co.kr/arti/society/society_general/1063454.html",
            "urlToImage": "https://flexible.img.hani.co.kr/flexible/normal/970/398/imgdb/child/2022/1020/16662255287502_20221019504203.jpg",
            "publishedAt": "2022-10-19T22:00:23Z",
            "content": "[] SPC , \r\n :2022-10-20 07:00 :2022-10-20 09:48"
        },
        {
            "source": {
                "id": null,
                "name": "Sisa-news.com"
            },
            "author": null,
            "title": "세계 골다공증의 날 맞아 뼈 건강 개선 위한 5단계 제안 - 시사뉴스",
            "description": "니옹, 스위스, 2022년 10월 20일 /PRNewswire/ -- 이달 20일 세계 골다공증의 날을 맞아, 국제골다공증재단(International Osteoporosis Foundation, IOF)이 뼈 건강을 개선하고, 골다공증을 예방하기 위한 단계를 선제적으로 진행하도록 전 연령층에 촉구했다.  골다공증은 전 세계 약 5억 명에게 발생하",
            "url": "http://www.sisa-news.com/news/article.html?no=216643",
            "urlToImage": "http://www.sisa-news.com/data/design/logo/default_image_share_20211231103110.png",
            "publishedAt": "2022-10-19T22:00:00Z",
            "content": ", , 2022 10 20 /PRNewswire/ --  20 , (International Osteoporosis Foundation, IOF) , .\r\n 5 , , . 50 3 1, 5 1 .\r\n , . , .\r\nIOF CEO Philippe Halbout \" \" \" \" . \" , , \" .\r\nIOF 5 .\r\n, D . D , .\r\n . . 1 , 1… [+412 chars]"
        },
        {
            "source": {
                "id": null,
                "name": "Manchester United"
            },
            "author": null,
            "title": "맨유, 토트넘에 2-0 승리 - Man Utd",
            "description": "맨체스터 유나이티드가 올드 트라포드에서 토트넘 홋스퍼를 2-0으로 제압했다. 프레드와 브루노 페르난데스의 득점포가 승리를 이끌었다.",
            "url": "https://www.manutd.com/ko/news/detail/match-report-and-video-highlights-man-utd-v-tottenham-19-october-2022",
            "urlToImage": "https://assets.manutd.com/AssetPicker/images/0/0/17/154/1153728/BF8I7872_96e597f0_d3b9_4c76_8f19_d66e49c125e51666213938849_large.jpg",
            "publishedAt": "2022-10-19T21:58:11Z",
            "content": "0-0 . 19 . .4-2-3-1 . , , , , , , , , , , \r\n, , , , , , , , , , 3-5-2 ."
        },
        {
            "source": {
                "id": null,
                "name": "Hankyung.com"
            },
            "author": null,
            "title": "\"흉흉한 증권사 건설사 상황\"…여의도 증권가에 퍼진 '찌라시' [김익환의 컴퍼니워치] - 한국경제",
            "description": "\"흉흉한 증권사 건설사 상황\"…여의도 증권가에 퍼진 '찌라시' [김익환의 컴퍼니워치], 김익환 기자, 뉴스",
            "url": "https://www.hankyung.com/finance/article/202210190014i",
            "urlToImage": "https://img.hankyung.com/photo/202210/01.31456214.1.jpg",
            "publishedAt": "2022-10-19T21:47:11Z",
            "content": "\"() 15% ... ...A, B , C, D .\"19 '' . . \"\" .\r\n(DCM) \" \" . \" \" . \r\n15% (CP) , . (PF) . . \r\n, . . 5~6% . 6 16822 . \r\n. 6 ( ) 6000 . 6091 . 3 1800. . 18 2000 . \r\n. 2050 (PF) (ABCP) . ABCP . . \r\n. (IB) AB… [+43 chars]"
        },
        {
            "source": {
                "id": null,
                "name": "Imbc.com"
            },
            "author": "김민형",
            "title": "거짓말 탐지기 거부한 김근식‥또 추가 피해자 - MBC뉴스",
            "description": "출소를 하루 앞두고 재구속된 아동 성범죄자 김근식이, 구속이 부당하다며 법원 판단을 요청했지만 받아들여지지 않았습니다. 한편 1999년 인천에서 김근식으로부터 강제추행...",
            "url": "https://imnews.imbc.com/replay/2022/nwtoday/article/6418789_35752.html",
            "urlToImage": "https://image.imnews.imbc.com/replay/2022/nwtoday/article/__icsFiles/afieldfile/2022/10/20/today_20221020_064332_2_6_Large.jpg",
            "publishedAt": "2022-10-19T21:44:16Z",
            "content": ", .\r\n1999 .\r\n.\r\n2006 13 .\r\n.\r\n\" , \" , \" \" .\r\n, .\r\n.\r\n1999, , KBS .\r\n\" \" .\r\n.\r\n\"20 \" .\r\n\" \" \" \" .\r\n' e' 4 .\r\nMBC .\r\nMBC 24 . \r\n02-784-4000mbcjebo@mbc.co.kr@mbc"
        },
        {
            "source": {
                "id": null,
                "name": "Mk.co.kr"
            },
            "author": "매일경제",
            "title": "'저금리 대출' 108억 챙긴 보이스피싱 주범 필리핀서 송환 - 매일경제",
            "description": "https://www.mk.co.kr/news/society/view/2022/10/927878/",
            "url": "https://www.mk.co.kr/news/society/view/2022/10/927878/",
            "urlToImage": "https://file.mk.co.kr/meet/yonhap/2022/10/20/image_readtop_2022_927878_0_083211.jpg",
            "publishedAt": "2022-10-19T21:00:07Z",
            "content": "20 20 .2017 '' 12 562 108 (· ) .\r\n' ' .\r\n\" \" .64 ' ' '', '' .\r\n2020 2 .\r\n5 9 4 . 4 .\r\n, 40 .\r\n\" \" \" \" .\r\n[]\r\nCopyrights ."
        },
        {
            "source": {
                "id": null,
                "name": "Ytn.co.kr"
            },
            "author": "안동준",
            "title": "\"같은 전화번호에 이름만 10개\"...중고거래 사기 신고 300건 포착 - YTN",
            "description": "[앵커]온라인에서 선입금을 요구한 뒤 물건을 보내지 않고 잠적하는 중고사기, 당해보신 분들도 계실 텐데요.최근 같은 전화번호를 서로 다른 이름 10개로 돌려...",
            "url": "https://www.ytn.co.kr/_ln/0103_202210200530576469",
            "urlToImage": "https://image.ytn.co.kr/general/jpg/2022/1020/202210200530576469_t.jpg",
            "publishedAt": "2022-10-19T20:30:00Z",
            "content": null
        },
        {
            "source": {
                "id": null,
                "name": "Asiae.co.kr"
            },
            "author": "https://www.asiae.co.kr",
            "title": "오늘 '간의 날'…4050 암사망률 1위 간암, 치료 발전으로 완치 가능성↑ - 아시아경제",
            "description": "매년 10월20일은 대한간학회가 제정한 '간의 날'이다. 간은 '침묵의 장기'로 불리는 만큼 심각한 손상이 생겨도 증상이 없기 때문에 조기 발견을 위한 적극적인 검진이 필요하다. 특히 모든 간 질환 중 가장 신체적, 경제적, 사회적 부담이 높은 것은 '간암'이다. 간암은 사회·경제적 활동이 활발한 4050 세대에 치명적인 것으로 나타났다. 통계청이 발표한 '2021년 사망원인통계'에 따르면 간암은 40대",
            "url": "https://www.asiae.co.kr/article/2022101923021407074",
            "urlToImage": "https://cphoto.asiae.co.kr/listimglink/1/2017100809125784650_1.jpg",
            "publishedAt": "2022-10-19T20:30:00Z",
            "content": "[=DB]\r\n[ ] 1020 ' '. ' ' . , , ''. · 4050 . '2021 ' 40 50 1 .\r\n . 20 . 80% , 1~5% .\r\n , , , . . , , , , . .\r\n . , . \" B 72% C , \" \" , \" .\r\n , , . , , .\r\n . 5cm , 3 ( 3cm ) . .\r\n . , . , (TACE). .\r\n ,… [+152 chars]"
        },
        {
            "source": {
                "id": null,
                "name": "Sporting News"
            },
            "author": null,
            "title": "[GOAL 리뷰] 'VAR 득점 취소' 마요르카, 소시에다드에 0-1 패…이강인 교체출전 - Goal.com",
            "description": "Get the latest soccer news, rumors, video highlights, scores, schedules, standings, photos, player information and more from Sporting News Canada",
            "url": "https://www.sportingnews.com/ca/soccer",
            "urlToImage": "https://static.sportingnews.com/1.17.0.11/themes/custom/tsn/logo.jpg",
            "publishedAt": "2022-10-19T20:09:01Z",
            "content": null
        },
        {
            "source": {
                "id": null,
                "name": "Hankyung.com"
            },
            "author": null,
            "title": "법사위 등 8개 상임위 국감…'민주당 압수수색' 쟁점 - 한국경제",
            "description": "법사위 등 8개 상임위 국감…'민주당 압수수색' 쟁점, 정치",
            "url": "https://www.hankyung.com/politics/article/202210200091Y",
            "urlToImage": "https://img.hankyung.com/photo/202210/ZK.31570090.1.jpg",
            "publishedAt": "2022-10-19T20:00:06Z",
            "content": "\" ' ' \" 20 \" \" . \" , \" . \" \" . \" \" . \" ' ' \" \" , \" . \" , \" \" \" . \" . ("
        },
        {
            "source": {
                "id": null,
                "name": "Voakorea.com"
            },
            "author": null,
            "title": "워싱턴 뉴스 광장 2022/10/20 - 한국어 방송 - VOA Korean",
            "description": "VOA 한국어 아침 뉴스 프로그램 '워싱턴 뉴스 광장' 2022년 10월 20일 방송입니다. 북한이 18일 밤부터 19일 오후까지 동해와 서해 완충구역으로 350여 발의 포병 사격을 가하면서 또 다시 9.19 남북군사합의를 위반했습니다. 미 국무부는 북한의 포 사격에 대해 모든 도발적 행동을 중단할 것을 촉구했습니다. 미국 헤리티지재단은 '2023 미국 군사력 지수' 보고서에서 북한의 핵을 가장 큰 군사적 위협 중 하나로 꼽았습니다. 방송 시간: 한반도 오전 …",
            "url": "https://www.voakorea.com/a/6777724.html",
            "urlToImage": "https://gdb.voanews.com/5f422d7d-22c1-412e-99c8-c525a1e94017_w1200_r1.png",
            "publishedAt": "2022-10-19T20:00:00Z",
            "content": "No media source currently available"
        },
        {
            "source": {
                "id": null,
                "name": "Yna.co.kr"
            },
            "author": "이상헌",
            "title": "美 \"北 포병사격 심각한 우려…대화가 비핵화 목표의 핵심\" - 연합뉴스",
            "description": "(워싱턴=연합뉴스) 이상헌 특파원 = 미국 국무부는 19일(현지시간) 북한의 계속되는 동·서해 완충구역 포사격 도발에 우려를 표하면서도 북한과의...",
            "url": "https://www.yna.co.kr/view/AKR20221020005300071",
            "urlToImage": "https://img4.yna.co.kr/etc/inner/KR/2022/10/20/AKR20221020005300071_01_i_P4.jpg",
            "publishedAt": "2022-10-19T19:03:28Z",
            "content": ", · [ . . . For Use Only in the Republic of Korea. No Redistribution] \r\n(=) = 19() · . \r\n \" \" \" \" .\r\n \" , \" .\r\n14 19 · 9·19 . \r\n , \" , , \" .\r\n .\r\n .\r\n \" \" \" \" .\r\n honeybee@yna.co.kr\r\n okjebo&lt;(c) ,… [+22 chars]"
        },
        {
            "source": {
                "id": null,
                "name": "Voakorea.com"
            },
            "author": null,
            "title": "생방송 여기는 워싱턴입니다 2022/10/20 아침 - 한국어 방송 - VOA Korean",
            "description": "세계 뉴스와 함께 미국의 모든 것을 소개하는 '생방송 여기는 워싱턴입니다', 2022년 10월 20일 아침 방송입니다. '지구촌 오늘'에서는 미국 등 서방국가가 이란의 러시아 무기지원 정황을 유엔 안전보장이사회 안건으로 제기하는 소식 전해드리고, '아메리카 나우'에서는 전략비축유 1천500만 배럴 추가 방출 계획 살펴보겠습니다. 방송 시간: 한반도 오전 4:00~5:00 (UTC 19:00~20:00).",
            "url": "https://www.voakorea.com/a/6777712.html",
            "urlToImage": "https://gdb.voanews.com/3fe13141-44ae-4db0-b943-35a048bac868_w1200_r1.png",
            "publishedAt": "2022-10-19T19:00:00Z",
            "content": "' ', 2022 10 20 . ' ' , ' ' 1500 . : 4:00~5:00 (UTC 19:00~20:00)."
        }
    ]
}